[
  {
    "icon": "/assets/img/testimonial/tes7-smoll-img.png",
    "subtitle": "Operating Officer",
    "title": "Shakib Mahmud",
    "desc": "I should be incapable of drawing a single stroke at the present moment; and yet I feel that I never was a best greater artist than now. The lovely valley teems with vapor around me, & the meridian sun strikes."
  },
  {
    "icon": "/assets/img/testimonial/tes7-smoll-img.png",
    "subtitle": "Operating Officer",
    "title": "Shakib Mahmud",
    "desc": "I should be incapable of drawing a single stroke at the present moment; and yet I feel that I never was a best greater artist than now. The lovely valley teems with vapor around me, & the meridian sun strikes."
  }
]
